freenom_dns/__init__.py
freenom_dns/app.py
freenom_dns/parse.py
freenom_dns/url.py
freenom_dns/utils.py
freenom_dns-2.0.1.dist-info/LICENSE
freenom_dns-2.0.1.dist-info/METADATA
freenom_dns-2.0.1.dist-info/WHEEL
freenom_dns-2.0.1.dist-info/top_level.txt
freenom_dns-2.0.1.dist-info/RECORD
