Metadata-Version: 2.1
Name: freenom-dns
Version: 2.0.1
Summary: An unofficial python implementation for managing freenom.com dns records.
Home-page: https://github.com/PunkLee2py/freenom-dns
Author: Punk Lee
Author-email: punklee333@gmail.com
License: MIT
Platform: UNKNOWN
Requires-Python: >=3.6
Requires-Dist: requests (>=2.24.0)
Requires-Dist: retrying (>=1.3.3)
Requires-Dist: lxml (>=4.5.2)
